ToolsForzky/ToolsForzky.py
ToolsForzky/_init_.py
ToolsForzky-0.1.1.dist-info/LICENSE
ToolsForzky-0.1.1.dist-info/METADATA
ToolsForzky-0.1.1.dist-info/WHEEL
ToolsForzky-0.1.1.dist-info/top_level.txt
ToolsForzky-0.1.1.dist-info/RECORD
