Metadata-Version: 2.1
Name: ToolsForzky
Version: 0.1.1
Summary: some tools for 302
Home-page: 
Author: zengkeyao
Author-email: cengkeyao186@Gmail.com
License: MIT License
Requires-Python: >=3
License-File: LICENSE
